pandaplotdocs/__init__.py
pandaplotdocs/_data.py
pandaplotdocs/_pdf.py
pandaplotdocs/generator.py
pandaplotdocs-0.1.0.dist-info/METADATA
pandaplotdocs-0.1.0.dist-info/WHEEL
pandaplotdocs-0.1.0.dist-info/top_level.txt
pandaplotdocs-0.1.0.dist-info/RECORD
