Metadata-Version: 2.4
Name: pandaplotdocs
Version: 0.1.0
Summary: Generates a PDF reference for essential Pandas and Matplotlib functions.
Home-page: 
Author: Anonymous
License: MIT
Keywords: pandas,matplotlib,documentation,pdf,reference
Classifier: Development Status :: 3 - Alpha
Classifier: Intended Audience :: Developers
Classifier: License :: OSI Approved :: MIT License
Classifier: Programming Language :: Python :: 3
Classifier: Programming Language :: Python :: 3.8
Classifier: Programming Language :: Python :: 3.9
Classifier: Programming Language :: Python :: 3.10
Classifier: Programming Language :: Python :: 3.11
Classifier: Operating System :: OS Independent
Classifier: Topic :: Documentation
Classifier: Topic :: Software Development :: Libraries :: Python Modules
Requires-Python: >=3.8, <4
Requires-Dist: fpdf2
Requires-Dist: defusedxml
Requires-Dist: Pillow
Requires-Dist: fonttools
Requires-Dist: setuptools
Dynamic: author
Dynamic: classifier
Dynamic: description
Dynamic: description-content-type
Dynamic: keywords
Dynamic: license
Dynamic: requires-dist
Dynamic: requires-python
Dynamic: summary
